nextcrop/QtImageViewer.py
nextcrop/__init__.py
nextcrop/annotateframe.py
nextcrop/annotateimage.py
nextcrop/cli.py
nextcrop/config.py
nextcrop/control.py
nextcrop/crop.py
nextcrop/cropimages.py
nextcrop/cropimageswithframe.py
nextcrop/cropwidget.py
nextcrop/files.py
nextcrop/fsmscan.py
nextcrop/guicrop.py
nextcrop/guicropframe.py
nextcrop/guifiles.py
nextcrop/guiimage.py
nextcrop/guiscan.py
nextcrop/main.py
nextcrop/manualcrop.py
nextcrop/mockscan.py
nextcrop/saveimages.py
nextcrop/scan.py
nextcrop/test2.py
nextcrop/test_classes.py
nextcrop/testimageviewer.py
nextcrop/testlabel.py
nextcrop/try_ioc.py
nextcrop/uicrop.py
nextcrop/uicropframe.py
nextcrop/uicropimage.py
nextcrop/uifiles.py
nextcrop/uiscan.py
nextcrop/gui/__init__.py
nextcrop/gui/main.py
nextcrop-0.0.12.dist-info/LICENSE
nextcrop-0.0.12.dist-info/METADATA
nextcrop-0.0.12.dist-info/WHEEL
nextcrop-0.0.12.dist-info/entry_points.txt
nextcrop-0.0.12.dist-info/top_level.txt
nextcrop-0.0.12.dist-info/RECORD
