Metadata-Version: 2.1
Name: nextcrop
Version: 0.0.12
Summary: Crop and dewkew scanned images
Home-page: https://github.com/pypa/sampleproject
Author: Markus Leuthold
Author-email: pypi@titlis.org
License: UNKNOWN
Platform: UNKNOWN
Classifier: Programming Language :: Python :: 3
Classifier: License :: OSI Approved :: MIT License
Classifier: Operating System :: OS Independent
Requires-Python: >=3.6
Requires-Dist: opencv-python
Requires-Dist: transitions
Requires-Dist: PySide2
Requires-Dist: simple-config
Requires-Dist: dependency-injector
